AES_Python/__init__.py
AES_Python/main.py
AES_Python-1.5.5.dist-info/LICENSE
AES_Python-1.5.5.dist-info/METADATA
AES_Python-1.5.5.dist-info/WHEEL
AES_Python-1.5.5.dist-info/top_level.txt
AES_Python-1.5.5.dist-info/RECORD
