Metadata-Version: 2.1
Name: AES_Python
Version: 1.5.5
Summary: AES (Advanced Encryption Standard) implementation in Python-3
Author-email: Gabriel Lindeblad <Gabriel.Lindeblad@icloud.com>
Project-URL: Homepage, https://github.com/Glindeb/AES-Python
Project-URL: Repository, https://github.com/Glindeb/AES-Python
Project-URL: Documentation, https://github.com/Glindeb/AES-Python
Keywords: AES,AES-Python,Advanced Encryption Standard,encryption,cryptography
Classifier: License :: OSI Approved :: MIT License
Classifier: Operating System :: OS Independent
Classifier: Topic :: Education
Classifier: Programming Language :: Python :: 3.11
Classifier: Programming Language :: Python :: 3.12
Requires-Python: >=3.11
License-File: LICENSE
Provides-Extra: dev
Requires-Dist: pytest ; extra == 'dev'
Requires-Dist: pytest-cov ; extra == 'dev'
Requires-Dist: mypy ; extra == 'dev'
Requires-Dist: flake8 ; extra == 'dev'
Requires-Dist: tox ; extra == 'dev'
